semantic_codebase_inspection/__init__.py
semantic_codebase_inspection/nlp_wrapper.py
semantic_codebase_inspection/semantic_codebase_inspection.py
semantic_codebase_inspection-0.1.2.dist-info/WHEEL
semantic_codebase_inspection-0.1.2.dist-info/METADATA
semantic_codebase_inspection-0.1.2.dist-info/RECORD
