Metadata-Version: 2.1
Name: semantic-codebase-inspection
Version: 0.1.2
Summary: Semantic Codebase Inspection helps developers familiarize themselves with a python project that has decent naming conventions. Dependencies not included.
Author: mandrewstuart
Author-email: andrew_matte_@hotmail.com
Requires-Python: >=3.10,<4.0
Classifier: Programming Language :: Python :: 3
Classifier: Programming Language :: Python :: 3.10
